{
    "playerStats": [],
    "points": 0,
    "averagePoints": 0,
    "id": "1179",
    "team": {
        "badgeColor": "https://assets-fantasy.llt-services.com/teambadge/t188/color/t188_real-sociedad.png",
        "badgeGray": "https://assets-fantasy.llt-services.com/teambadge/t188/gray/t188_real-sociedad.png",
        "badgeWhite": "https://assets-fantasy.llt-services.com/teambadge/t188/white/t188_real-sociedad.png",
        "name": "Real Sociedad",
        "id": "16",
        "shortName": "RSO",
        "slug": "real-sociedad",
        "dspId": 84,
        "store": ""
    },
    "name": "Diego Rico Salguero",
    "lastSeasonPoints": 78,
    "nickname": "Diego Rico",
    "slug": "diego-rico",
    "positionId": 2,
    "position": "Defensa",
    "marketValue": {
        "13/07/2023": 6000000,
        "14/07/2023": 5995789,
        "15/07/2023": 5991746,
        "16/07/2023": 5873163,
        "17/07/2023": 5763980,
        "18/07/2023": 5637352,
        "19/07/2023": 5531638,
        "20/07/2023": 5469251,
        "21/07/2023": 5355283,
        "22/07/2023": 5234046,
        "23/07/2023": 5126226,
        "24/07/2023": 5022030,
        "25/07/2023": 4899192,
        "26/07/2023": 4796458,
        "27/07/2023": 4702411,
        "28/07/2023": 4605930,
        "29/07/2023": 4504914,
        "30/07/2023": 4415955,
        "31/07/2023": 4320442,
        "01/08/2023": 4224879,
        "02/08/2023": 4131206,
        "03/08/2023": 4047404,
        "04/08/2023": 3950388,
        "05/08/2023": 3867670
    },
    "playerStatus": "ok"
}