{
    "playerStats": [],
    "points": 0,
    "averagePoints": 0,
    "id": "1216",
    "team": {
        "badgeColor": "https://assets-fantasy.llt-services.com/teambadge/t188/color/t188_real-sociedad.png",
        "badgeGray": "https://assets-fantasy.llt-services.com/teambadge/t188/gray/t188_real-sociedad.png",
        "badgeWhite": "https://assets-fantasy.llt-services.com/teambadge/t188/white/t188_real-sociedad.png",
        "name": "Real Sociedad",
        "id": "16",
        "shortName": "RSO",
        "slug": "real-sociedad",
        "dspId": 84,
        "store": ""
    },
    "name": "Jon Pacheco",
    "lastSeasonPoints": 67,
    "nickname": "Jon Pacheco",
    "slug": "jon-pacheco",
    "positionId": 2,
    "position": "Defensa",
    "marketValue": {
        "13/07/2023": 4300000,
        "14/07/2023": 4296982,
        "15/07/2023": 4294084,
        "16/07/2023": 4215211,
        "17/07/2023": 4119220,
        "18/07/2023": 4009456,
        "19/07/2023": 3904927,
        "20/07/2023": 3798193,
        "21/07/2023": 3691514,
        "22/07/2023": 3606329,
        "23/07/2023": 3510819,
        "24/07/2023": 3413555,
        "25/07/2023": 3323826,
        "26/07/2023": 3235171,
        "27/07/2023": 3148119,
        "28/07/2023": 3059095,
        "29/07/2023": 2980095,
        "30/07/2023": 2904271,
        "31/07/2023": 2828587,
        "01/08/2023": 2751279,
        "02/08/2023": 2677628,
        "03/08/2023": 2608370,
        "04/08/2023": 2547282,
        "05/08/2023": 2478829
    },
    "playerStatus": "ok"
}