{
    "playerStats": [],
    "points": 0,
    "averagePoints": 0,
    "id": "274",
    "team": {
        "badgeColor": "https://assets-fantasy.llt-services.com/teambadge/t188/color/t188_real-sociedad.png",
        "badgeGray": "https://assets-fantasy.llt-services.com/teambadge/t188/gray/t188_real-sociedad.png",
        "badgeWhite": "https://assets-fantasy.llt-services.com/teambadge/t188/white/t188_real-sociedad.png",
        "name": "Real Sociedad",
        "id": "16",
        "shortName": "RSO",
        "slug": "real-sociedad",
        "dspId": 84,
        "store": ""
    },
    "name": "Alejandro Remiro Gargallo",
    "lastSeasonPoints": 230,
    "nickname": "Remiro",
    "slug": "remiro",
    "positionId": 1,
    "position": "Portero",
    "marketValue": {
        "13/07/2023": 22500000,
        "14/07/2023": 22484209,
        "15/07/2023": 22469050,
        "16/07/2023": 22712967,
        "17/07/2023": 23185422,
        "18/07/2023": 23678522,
        "19/07/2023": 24375289,
        "20/07/2023": 24883499,
        "21/07/2023": 25332422,
        "22/07/2023": 26010213,
        "23/07/2023": 26729788,
        "24/07/2023": 27197685,
        "25/07/2023": 27886161,
        "26/07/2023": 28428896,
        "27/07/2023": 29011853,
        "28/07/2023": 29477825,
        "29/07/2023": 29906089,
        "30/07/2023": 30328488,
        "31/07/2023": 30807545,
        "01/08/2023": 31170235,
        "02/08/2023": 31586210,
        "03/08/2023": 31937226,
        "04/08/2023": 32283055,
        "05/08/2023": 32622473
    },
    "playerStatus": "ok"
}