{
    "playerStats": [],
    "points": 0,
    "averagePoints": 0,
    "id": "1039",
    "team": {
        "badgeColor": "https://assets-fantasy.llt-services.com/teambadge/t184/color/t184_rayo-vallecano.png",
        "badgeGray": "https://assets-fantasy.llt-services.com/teambadge/t184/gray/t184_rayo-vallecano.png",
        "badgeWhite": "https://assets-fantasy.llt-services.com/teambadge/t184/white/t184_rayo-vallecano.png",
        "name": "Rayo Vallecano",
        "id": "14",
        "shortName": "RAY",
        "slug": "rayo-vallecano",
        "dspId": 80,
        "store": ""
    },
    "name": "Jos\u00e9 Pozo",
    "lastSeasonPoints": 12,
    "nickname": "Jos\u00e9 Pozo",
    "slug": "jose-pozo",
    "positionId": 3,
    "position": "Centrocampista",
    "marketValue": {
        "13/07/2023": 1150000,
        "14/07/2023": 1149192,
        "15/07/2023": 1148417,
        "16/07/2023": 1109244,
        "17/07/2023": 1071957,
        "18/07/2023": 1037351,
        "19/07/2023": 1004250,
        "20/07/2023": 972966,
        "21/07/2023": 942063,
        "22/07/2023": 912679,
        "23/07/2023": 885069,
        "24/07/2023": 858653,
        "25/07/2023": 833982,
        "26/07/2023": 810029,
        "27/07/2023": 786859,
        "28/07/2023": 764480,
        "29/07/2023": 743580,
        "30/07/2023": 723863,
        "31/07/2023": 705139,
        "01/08/2023": 687226,
        "02/08/2023": 669674,
        "03/08/2023": 652683,
        "04/08/2023": 636004,
        "05/08/2023": 619669
    },
    "playerStatus": "ok"
}