{
    "playerStats": [],
    "points": 0,
    "averagePoints": 0,
    "id": "67",
    "team": {
        "badgeColor": "https://assets-fantasy.llt-services.com/teambadge/t175/color/t175_atletico-de-madrid.png",
        "badgeGray": "https://assets-fantasy.llt-services.com/teambadge/t175/gray/t175_atletico-de-madrid.png",
        "badgeWhite": "https://assets-fantasy.llt-services.com/teambadge/t175/white/t175_atletico-de-madrid.png",
        "name": "Atl\u00e9tico de Madrid",
        "id": "2",
        "shortName": "ATM",
        "slug": "atletico-de-madrid",
        "dspId": 70,
        "store": ""
    },
    "name": "Marcos Llorente",
    "lastSeasonPoints": 109,
    "nickname": "Marcos Llorente",
    "slug": "llorente-marcos",
    "positionId": 3,
    "position": "Centrocampista",
    "marketValue": {
        "13/07/2023": 26000000,
        "14/07/2023": 25981753,
        "15/07/2023": 25964235,
        "16/07/2023": 25921766,
        "17/07/2023": 25851701,
        "18/07/2023": 25809601,
        "19/07/2023": 25887468,
        "20/07/2023": 25989175,
        "21/07/2023": 26162646,
        "22/07/2023": 26311494,
        "23/07/2023": 26576659,
        "24/07/2023": 26779401,
        "25/07/2023": 26983412,
        "26/07/2023": 27189748,
        "27/07/2023": 27332475,
        "28/07/2023": 27436690,
        "29/07/2023": 27651067,
        "30/07/2023": 27792111,
        "31/07/2023": 27919060,
        "01/08/2023": 28034679,
        "02/08/2023": 28189416,
        "03/08/2023": 28235053,
        "04/08/2023": 28068794,
        "05/08/2023": 27814921
    },
    "playerStatus": "ok"
}