{
    "playerStats": [],
    "points": 0,
    "averagePoints": 0,
    "id": "817",
    "team": {
        "badgeColor": "https://assets-fantasy.llt-services.com/teambadge/t1737/color/t1737_cadiz-cf.png",
        "badgeGray": "https://assets-fantasy.llt-services.com/teambadge/t1737/gray/t1737_cadiz-cf.png",
        "badgeWhite": "https://assets-fantasy.llt-services.com/teambadge/t1737/white/t1737_cadiz-cf.png",
        "name": "C\u00e1diz CF",
        "id": "162",
        "shortName": "CAD",
        "slug": "cadiz-cf",
        "dspId": 67,
        "store": ""
    },
    "name": "Alejandro Fern\u00e1ndez Iglesias",
    "lastSeasonPoints": 104,
    "nickname": "\u00c1lex Fern\u00e1ndez",
    "slug": "alex",
    "positionId": 3,
    "position": "Centrocampista",
    "marketValue": {
        "13/07/2023": 7000000,
        "14/07/2023": 6995087,
        "15/07/2023": 6990370,
        "16/07/2023": 7059209,
        "17/07/2023": 6884492,
        "18/07/2023": 6667121,
        "19/07/2023": 6448625,
        "20/07/2023": 6237705,
        "21/07/2023": 6041942,
        "22/07/2023": 5843489,
        "23/07/2023": 5656672,
        "24/07/2023": 5466358,
        "25/07/2023": 5290145,
        "26/07/2023": 5124438,
        "27/07/2023": 4955646,
        "28/07/2023": 4793197,
        "29/07/2023": 4637133,
        "30/07/2023": 4489371,
        "31/07/2023": 4343784,
        "01/08/2023": 4210681,
        "02/08/2023": 4076286,
        "03/08/2023": 3947416,
        "04/08/2023": 3823048,
        "05/08/2023": 3699914
    },
    "playerStatus": "injured"
}