{
    "playerStats": [],
    "points": 0,
    "averagePoints": 0,
    "id": "650",
    "team": {
        "badgeColor": "https://assets-fantasy.llt-services.com/teambadge/t450/color/t450_c-a-osasuna.png",
        "badgeGray": "https://assets-fantasy.llt-services.com/teambadge/t450/gray/t450_c-a-osasuna.png",
        "badgeWhite": "https://assets-fantasy.llt-services.com/teambadge/t450/white/t450_c-a-osasuna.png",
        "name": "C.A. Osasuna",
        "id": "13",
        "shortName": "OSA",
        "slug": "c-a-osasuna",
        "dspId": 190,
        "store": ""
    },
    "name": "David Garc\u00eda Zubir\u00eda",
    "lastSeasonPoints": 156,
    "nickname": "David Garc\u00eda",
    "slug": "david-garcia",
    "positionId": 2,
    "position": "Defensa",
    "marketValue": {
        "13/07/2023": 20000000,
        "14/07/2023": 19985964,
        "15/07/2023": 19972489,
        "16/07/2023": 19747692,
        "17/07/2023": 20147706,
        "18/07/2023": 20603993,
        "19/07/2023": 21069820,
        "20/07/2023": 21442272,
        "21/07/2023": 21925264,
        "22/07/2023": 22460331,
        "23/07/2023": 22898191,
        "24/07/2023": 23321794,
        "25/07/2023": 23901489,
        "26/07/2023": 24407856,
        "27/07/2023": 24819751,
        "28/07/2023": 25242866,
        "29/07/2023": 25570080,
        "30/07/2023": 26026027,
        "31/07/2023": 26461562,
        "01/08/2023": 26807495,
        "02/08/2023": 27307822,
        "03/08/2023": 27736132,
        "04/08/2023": 28046175,
        "05/08/2023": 28508841
    },
    "playerStatus": "ok"
}